my_own_package/__init__.py
DanDFG_First_Package-0.2.0.dist-info/METADATA
DanDFG_First_Package-0.2.0.dist-info/WHEEL
DanDFG_First_Package-0.2.0.dist-info/top_level.txt
DanDFG_First_Package-0.2.0.dist-info/RECORD
