Metadata-Version: 2.1
Name: DanDFG-First-Package
Version: 0.2.0
Summary: My first package
Author: Daniel DFG
Author-email: danieldfgro2000@gmail.com
